PT_Pool/PT_Pool.py
PT_Pool/__init__.py
PT_Pool-0.0.4.dist-info/LICENSE
PT_Pool-0.0.4.dist-info/METADATA
PT_Pool-0.0.4.dist-info/WHEEL
PT_Pool-0.0.4.dist-info/top_level.txt
PT_Pool-0.0.4.dist-info/RECORD
