Metadata-Version: 2.1
Name: PT-Pool
Version: 0.0.4
Summary: Distibutes tasks among processes and threads.
Home-page: https://github.com/michalmonday/PT_Pool
Author: Michal Borowski
Author-email: michalmonday17@gmail.com
License: UNKNOWN
Project-URL: Bug Tracker, https://github.com/michalmonday/PT_Pool/issues
Platform: UNKNOWN
Classifier: Programming Language :: Python :: 3
Classifier: License :: OSI Approved :: MIT License
Classifier: Operating System :: OS Independent
Requires-Python: >=3.5
License-File: LICENSE
